{
 "x": [],
 "insta": [],
 "threads": [],
 "tiktok": [
  {
   "account": "newjeans_official",
   "title": "Happy B-DAY💛🐰 #Happy3rdBunniesDay  #Bunnies#버니즈 #NewJeans #뉴진스",
   "views": 20400000,
   "likes": 0,
   "cmts": 0,
   "cover": "https://p16-common-sign.tiktokcdn.com/tos-alisg-p-0037/o0IKsI0ALutJyfuBBAEuEgiAlAABQwP1idBA6n~tplv-tiktokx-origin.image?dr=14575&x-expires=1784890800&x-signature=1%2F6xPBLBHN7jNbc4Sp67RXuqYNI%3D&t=4d5b0474&ps=13740610&shp=81f88b70&shcp=43f4a2f9&idc=my3",
   "time": 1761703575,
   "url": "https://www.tiktok.com/@newjeans_official/video/7566459243893771536",
   "region": "kr"
  },
  {
   "account": "bts_official_bighit",
   "title": "BTS Family Photo Short Clip #2026BTSFESTA #BTS13thAnniversary",
   "views": 14000000,
   "likes": 0,
   "cmts": 0,
   "cover": "https://p16-common-sign.tiktokcdn.com/tos-alisg-p-0037/oIeiQcojAIoIvBGfDAALiQ3uIehyU7IE2Ad7AA~tplv-tiktokx-origin.image?dr=14575&x-expires=1784890800&x-signature=7vg5Gx8zvYGygqII2AjaOlyY2ek%3D&t=4d5b0474&ps=13740610&shp=81f88b70&shcp=43f4a2f9&idc=my3",
   "time": 1780499384,
   "url": "https://www.tiktok.com/@bts_official_bighit/video/7647186628812836116",
   "region": "kr"
  },
  {
   "account": "bts_official_bighit",
   "title": "Caught #jhope off camera 👀",
   "views": 13500000,
   "likes": 0,
   "cmts": 0,
   "cover": "https://p16-common-sign.tiktokcdn.com/tos-alisg-p-0037/oAo7jUH8OYjQIBTLDAQ9efW8RgfAhXQMIwoCqw~tplv-tiktokx-origin.image?dr=14575&x-expires=1784890800&x-signature=2sl7EmRnMtxdw3mZbAcQeXMXhUI%3D&t=4d5b0474&ps=13740610&shp=81f88b70&shcp=43f4a2f9&idc=my3",
   "time": 1780319040,
   "url": "https://www.tiktok.com/@bts_official_bighit/video/7646412054026325268",
   "region": "kr"
  },
  {
   "account": "newjeans_official",
   "title": "Happy 3rd Bunnies Day 🧸🐱🦦🐹🐶💛🐰 #Happy3rdBunniesDay  #Bunnies #버니즈 #NewJeans #뉴진스",
   "views": 12200000,
   "likes": 0,
   "cmts": 0,
   "cover": "https://p16-common-sign.tiktokcdn.com/tos-alisg-p-0037/oEfC4AFAWIDXYgAAWOAgfzErpBQGVSbBUAzJKC~tplv-tiktokx-origin.image?dr=14575&x-expires=1784890800&x-signature=fsWPPwiUBlxxPfI1irl0ceXtOYg%3D&t=4d5b0474&ps=13740610&shp=81f88b70&shcp=43f4a2f9&idc=my3",
   "time": 1761646041,
   "url": "https://www.tiktok.com/@newjeans_official/video/7566212134716149010",
   "region": "kr"
  },
  {
   "account": "bts_official_bighit",
   "title": "#KEEPSWIMMING with BTS.  To everyone who keeps swimming no matter what, we send our love and support.",
   "views": 10900000,
   "likes": 0,
   "cmts": 0,
   "cover": "https://p16-common-sign.tiktokcdn.com/tos-alisg-p-0037/oMAIwi1AInJE1AUftAIFAq6HElyBCBiWKa1Aiu~tplv-tiktokx-origin.image?dr=14575&x-expires=1784890800&x-signature=k9BFY8cnFj%2FOuIjdYaV3l4eyjzg%3D&t=4d5b0474&ps=13740610&shp=81f88b70&shcp=43f4a2f9&idc=my3",
   "time": 1781355430,
   "url": "https://www.tiktok.com/@bts_official_bighit/video/7650863317510147349",
   "region": "kr"
  },
  {
   "account": "newjeans_official",
   "title": "[NewJeans Day🎂]  Did You See The White Furry Animal? 🐇  #NewJeans #뉴진스 #NewJeansDay #NewJeans_4th_Anniversary",
   "views": 9600000,
   "likes": 0,
   "cmts": 0,
   "cover": "https://p16-common-sign.tiktokcdn.com/tos-alisg-p-0037/osIAQ4oexhPIomIjhivUwALQIA9GeCADAYXAfE~tplv-tiktokx-origin.image?dr=14575&x-expires=1784890800&x-signature=TIcq6bZmQdyqf%2BE4A88Yh1%2BLrgw%3D&t=4d5b0474&ps=13740610&shp=81f88b70&shcp=43f4a2f9&idc=my3",
   "time": 1784646153,
   "url": "https://www.tiktok.com/@newjeans_official/video/7664996863778622738",
   "region": "kr"
  },
  {
   "account": "bts_official_bighit",
   "title": "BTS ‘Rolling Stone’ Short Film #BTS #방탄소년단",
   "views": 7800000,
   "likes": 0,
   "cmts": 0,
   "cover": "https://p16-common-sign.tiktokcdn.com/tos-alisg-p-0037/oEA9jDgKHxAABIm82LvBa4AREiYAaiAEnlrY1~tplv-tiktokx-origin.image?dr=14575&x-expires=1784890800&x-signature=R8mAjBlbHaa6MGaHwuPS3P7mRT0%3D&t=4d5b0474&ps=13740610&shp=81f88b70&shcp=43f4a2f9&idc=my3",
   "time": 1779098461,
   "url": "https://www.tiktok.com/@bts_official_bighit/video/7641169709139758344",
   "region": "kr"
  },
  {
   "account": "bts_official_bighit",
   "title": "What are the FIRST 3 Words Define You? #SUGA #슈가 #BTS_NORMAL",
   "views": 7500000,
   "likes": 0,
   "cmts": 0,
   "cover": "https://p16-common-sign.tiktokcdn.com/tos-alisg-p-0037/oI0i1CBPEgIKBQAn4f5bZIOI1EAyFB8JLAiwAA~tplv-tiktokx-origin.image?dr=14575&x-expires=1784890800&x-signature=OnjywoyNPEKcJFn8nVS4aJi63J8%3D&t=4d5b0474&ps=13740610&shp=81f88b70&shcp=43f4a2f9&idc=my3",
   "time": 1784268874,
   "url": "https://www.tiktok.com/@bts_official_bighit/video/7663376464665906452",
   "region": "kr"
  },
  {
   "account": "bts_official_bighit",
   "title": "What are the FIRST 3 Words Define You? #jhope #제이홉 #BTS_NORMAL",
   "views": 5600000,
   "likes": 0,
   "cmts": 0,
   "cover": "https://p16-common-sign.tiktokcdn.com/tos-alisg-p-0037/oMQMzUMIAC5G8Aj9GrQASLIDCkGeEsGdZeexMo~tplv-tiktokx-origin.image?dr=14575&x-expires=1784890800&x-signature=yeT2xViN7chzojy0CXaLp6Ct%2Bys%3D&t=4d5b0474&ps=13740610&shp=81f88b70&shcp=43f4a2f9&idc=my3",
   "time": 1784268888,
   "url": "https://www.tiktok.com/@bts_official_bighit/video/7663376523084188949",
   "region": "kr"
  },
  {
   "account": "newjeans_official",
   "title": "[NewJeans Day🎂]  2026 Summer of NewJeans : HYEIN #NewJeans #뉴진스 #NewJeansDay #NewJeans_4th_Anniversary",
   "views": 5400000,
   "likes": 0,
   "cmts": 0,
   "cover": "https://p16-common-sign.tiktokcdn.com/tos-alisg-p-0037/oQAHExPVGgFeYfCPAcLA4pjH1EeIUADQIuApIv~tplv-tiktokx-origin.image?dr=14575&x-expires=1784890800&x-signature=19hbuWmO16lKBgV4D9SjmyII2sw%3D&t=4d5b0474&ps=13740610&shp=81f88b70&shcp=43f4a2f9&idc=my3",
   "time": 1784646110,
   "url": "https://www.tiktok.com/@newjeans_official/video/7664996681003437319",
   "region": "kr"
  },
  {
   "account": "le_sserafim",
   "title": "𝘽𝙊𝙊𝙈𝙋𝘼𝙇𝘼 𝙞𝙨 𝙘𝙤𝙢𝙞𝙣𝙜 ✮  #BOOMPALA",
   "views": 5200000,
   "likes": 0,
   "cmts": 0,
   "cover": "https://p16-common-sign.tiktokcdn.com/tos-alisg-p-0037/oY7QEjiBYvALkigAAIDAsB5AaAEExUNI8inQE~tplv-tiktokx-origin.image?dr=14575&x-expires=1784890800&x-signature=hnxeJpC%2Bp5E9T8p4j7Yuazwi3XA%3D&t=4d5b0474&ps=13740610&shp=81f88b70&shcp=43f4a2f9&idc=my3",
   "time": 1779109193,
   "url": "https://www.tiktok.com/@le_sserafim/video/7641215800082173192",
   "region": "kr"
  },
  {
   "account": "aespa_official",
   "title": "likezip #aespa #WINTER",
   "views": 5100000,
   "likes": 0,
   "cmts": 0,
   "cover": "https://p16-common-sign.tiktokcdn.com/tos-alisg-p-0037/o0dE7BcDqBEjAiVFE2uRoAI9EBUFfRbgfRIUR8~tplv-tiktokx-origin.image?dr=14575&x-expires=1784890800&x-signature=kkb9jggJkPCh%2BEKsATYCK6%2BbCzU%3D&t=4d5b0474&ps=13740610&shp=81f88b70&shcp=43f4a2f9&idc=my3",
   "time": 1782911296,
   "url": "https://www.tiktok.com/@aespa_official/video/7657545710342016263",
   "region": "kr"
  },
  {
   "account": "zachking",
   "title": "a message to all AI",
   "views": 50500000,
   "likes": 0,
   "cmts": 0,
   "cover": "https://p19-common-sign.tiktokcdn.com/tos-useast5-p-0068-tx/o8mI3fhVDDEPkSr4JQFBgmQERAllAh8fEACqAA~tplv-tiktokx-origin.image?dr=14575&x-expires=1784890800&x-signature=bKI44K413PIz6ESYhaqoJFaKdOw%3D&t=4d5b0474&ps=13740610&shp=81f88b70&shcp=43f4a2f9&idc=my3",
   "time": 1782319524,
   "url": "https://www.tiktok.com/@zachking/video/7655004069190192398",
   "region": "gl"
  },
  {
   "account": "charlidamelio",
   "title": "",
   "views": 43400000,
   "likes": 0,
   "cmts": 0,
   "cover": "https://p16-common-sign.tiktokcdn.com/tos-useast5-p-0068-tx/ooKHooGeLNLNtj1SfjwkACMIIJtggkEeAUYJQI~tplv-tiktokx-origin.image?dr=14575&x-expires=1784890800&x-signature=dv2zWHm7X543ZdEKI6tLivc6u2w%3D&t=4d5b0474&ps=13740610&shp=81f88b70&shcp=43f4a2f9&idc=my3",
   "time": 1784334114,
   "url": "https://www.tiktok.com/@charlidamelio/video/7663656667132857613",
   "region": "gl"
  },
  {
   "account": "espn",
   "title": "@Omar Raja surprised these Spurs fans sitting in the last row with courtside access for Wemby’s pregame warmup, a chance",
   "views": 33100000,
   "likes": 0,
   "cmts": 0,
   "cover": "https://p16-common-sign.tiktokcdn.com/tos-useast8-p-0068-tx2/oUC8AruXeLShCIqLgUIGvJesg3QaAdc1IqenDj~tplv-tiktokx-origin.image?dr=14575&x-expires=1784890800&x-signature=SOSYNh%2BZ1%2FHq4YOq9IlItNwlHQw%3D&t=4d5b0474&ps=13740610&shp=81f88b70&shcp=43f4a2f9&idc=my3",
   "time": 1781487155,
   "url": "https://www.tiktok.com/@espn/video/7651429072177794334",
   "region": "gl"
  },
  {
   "account": "zachking",
   "title": "Which one is cake? 🍰",
   "views": 17300000,
   "likes": 0,
   "cmts": 0,
   "cover": "https://p16-common-sign.tiktokcdn.com/tos-useast5-p-0068-tx/o0BE8onuE6kESjUC3ThDfD6RLoAFAA6gAmxqIf~tplv-tiktokx-origin.image?dr=14575&x-expires=1784890800&x-signature=tcsyZGlK8RvcMioTSTE3CZZHKQA%3D&t=4d5b0474&ps=13740610&shp=81f88b70&shcp=43f4a2f9&idc=my3",
   "time": 1783866039,
   "url": "https://www.tiktok.com/@zachking/video/7661646300332494094",
   "region": "gl"
  },
  {
   "account": "charlidamelio",
   "title": "dc @sadie",
   "views": 15900000,
   "likes": 0,
   "cmts": 0,
   "cover": "https://p16-common-sign.tiktokcdn.com/tos-useast5-p-0068-tx/o0giUZv7buBIlB21iCTvVacVpNI4ZnEvoAxkB~tplv-tiktokx-origin.image?dr=14575&x-expires=1784890800&x-signature=bh3ZTwHMxj85ED2to3ay4bRbDC0%3D&t=4d5b0474&ps=13740610&shp=81f88b70&shcp=43f4a2f9&idc=my3",
   "time": 1784434268,
   "url": "https://www.tiktok.com/@charlidamelio/video/7664086824247250190",
   "region": "gl"
  },
  {
   "account": "charlidamelio",
   "title": "",
   "views": 14700000,
   "likes": 0,
   "cmts": 0,
   "cover": "https://p16-common-sign.tiktokcdn.com/tos-useast5-p-0068-tx/osAHBVrbxYUIfCErfVDfbILhkt8jECFAtT4IW5~tplv-tiktokx-origin.image?dr=14575&x-expires=1784890800&x-signature=%2F2YC8HxAKHkBVtEvPFT16VmtZow%3D&t=4d5b0474&ps=13740610&shp=81f88b70&shcp=43f4a2f9&idc=my3",
   "time": 1784410420,
   "url": "https://www.tiktok.com/@charlidamelio/video/7663984400434072845",
   "region": "gl"
  },
  {
   "account": "zachking",
   "title": "@HappyKelli",
   "views": 13600000,
   "likes": 0,
   "cmts": 0,
   "cover": "https://p16-common-sign.tiktokcdn.com/tos-useast5-p-0068-tx/ogi09azIPANiiA6i6BB57g4OwAkAgAOqEJAYE~tplv-tiktokx-origin.image?dr=14575&x-expires=1784890800&x-signature=zLgQKIlseDw7htdPFQx7oFPAVqQ%3D&t=4d5b0474&ps=13740610&shp=81f88b70&shcp=43f4a2f9&idc=my3",
   "time": 1780497174,
   "url": "https://www.tiktok.com/@zachking/video/7647177136796617998",
   "region": "gl"
  },
  {
   "account": "bellapoarch",
   "title": "With one of the boys🐇 brb",
   "views": 11500000,
   "likes": 0,
   "cmts": 0,
   "cover": "https://p16-common-sign.tiktokcdn.com/tos-useast8-p-0068-tx2/oUMVsm8zAefIUXAI0seEADq4QWIIREZAjzAAF5~tplv-tiktokx-origin.image?dr=14575&x-expires=1784890800&x-signature=CmozCVL0LZpNzdRlTC9ZoaDQPd8%3D&t=4d5b0474&ps=13740610&shp=81f88b70&shcp=43f4a2f9&idc=my3",
   "time": 1781286478,
   "url": "https://www.tiktok.com/@bellapoarch/video/7650567168672763166",
   "region": "gl"
  },
  {
   "account": "khaby.lame",
   "title": "It all happened too fast😰#learnfromkhaby #comedy",
   "views": 11400000,
   "likes": 0,
   "cmts": 0,
   "cover": "https://p16-common-sign.tiktokcdn.com/tos-useast8-p-0068-tx2/o8iiAVIZ9mBXjYARDIkoTXd2PAxnpmLBBKaEi~tplv-tiktokx-origin.image?dr=14575&x-expires=1784890800&x-signature=%2BXLmkUE%2Bdc3Ayr4lhz2twW7wD2Y%3D&t=4d5b0474&ps=13740610&shp=81f88b70&shcp=43f4a2f9&idc=my3",
   "time": 1783259976,
   "url": "https://www.tiktok.com/@khaby.lame/video/7659043280474180895",
   "region": "gl"
  },
  {
   "account": "charlidamelio",
   "title": "using this as a fit check dc @shanewiththebody",
   "views": 11200000,
   "likes": 0,
   "cmts": 0,
   "cover": "https://p16-common-sign.tiktokcdn.com/tos-useast5-p-0068-tx/okI9c11CkAnoGwIgw3IARiiBV6BWQLCBof8nxp~tplv-tiktokx-origin.image?dr=14575&x-expires=1784890800&x-signature=%2B7wULsIPvkuFbP%2FHwkAIMPKfazU%3D&t=4d5b0474&ps=13740610&shp=81f88b70&shcp=43f4a2f9&idc=my3",
   "time": 1784474354,
   "url": "https://www.tiktok.com/@charlidamelio/video/7664258992201305357",
   "region": "gl"
  },
  {
   "account": "fifaworldcup",
   "title": "#FIFAWorldCup",
   "views": 11200000,
   "likes": 0,
   "cmts": 0,
   "cover": "https://p16-common-sign.tiktokcdn.com/tos-no1a-i-photomode-no/e094d93d24cc4adb8a599ffe3a8df390~tplv-photomode-image.jpeg?dr=14555&x-expires=1784890800&x-signature=J1KOD4VPDiEG5cipAeVM4wP7I0E%3D&t=4d5b0474&ps=13740610&shp=81f88b70&shcp=9b759fb9&idc=my3&ftpl=1",
   "time": 1784498548,
   "url": "https://www.tiktok.com/@fifaworldcup/video/7664362905856380183",
   "region": "gl"
  },
  {
   "account": "espn",
   "title": "@Omar Raja surprised these fans in the last row with a chance to high-five the team before they took the ice, a hockey s",
   "views": 10600000,
   "likes": 0,
   "cmts": 0,
   "cover": "https://p16-common-sign.tiktokcdn.com/tos-useast5-p-0068-tx/oETIHWfk0QACdA7DRCIEYfAeaAEswEDBUIojAF~tplv-tiktokx-origin.image?dr=14575&x-expires=1784890800&x-signature=zQwcTV%2FYdIB9KKBrKEVTGSxRG6M%3D&t=4d5b0474&ps=13740610&shp=81f88b70&shcp=43f4a2f9&idc=my3",
   "time": 1781272702,
   "url": "https://www.tiktok.com/@espn/video/7650508003224866061",
   "region": "gl"
  }
 ],
 "reddit": [],
 "disaster": [],
 "updated": "2026-07-22T20:13:55.370299+09:00"
}