[
  {
    "title": "EBS/RESET(2026.07.17)-2",
    "url": "https://blog.naver.com/universalfather0/224349202221",
    "sources": [
      "네이버블로그",
      "네이버카페",
      "더쿠"
    ],
    "source_count": 3,
    "platform_count": 2,
    "posts": 29,
    "src_posts": {
      "더쿠": 1,
      "네이버카페": 26,
      "네이버블로그": 2
    },
    "age_h": 0.9,
    "burst": 12.88
  },
  {
    "title": "전세사기 당한 26살 스스로 목숨 끊어",
    "url": "https://www.issuelink.co.kr/community/go/fmkorea/10104980620",
    "sources": [
      "에펨코리아",
      "인벤"
    ],
    "source_count": 2,
    "platform_count": 2,
    "posts": 2,
    "src_posts": {
      "에펨코리아": 1,
      "인벤": 1
    },
    "age_h": 2.3,
    "burst": 9.88
  },
  {
    "title": "치과 치료때 가슴 덮친다는 간호사. jpg",
    "url": "https://www.issuelink.co.kr/community/go/mlbpark/117366704",
    "sources": [
      "엠팍",
      "웃대"
    ],
    "source_count": 2,
    "platform_count": 2,
    "posts": 2,
    "src_posts": {
      "웃대": 1,
      "엠팍": 1
    },
    "age_h": 2.3,
    "burst": 9.88
  }
]