[
  {
    "title": "EBS/RESET(2026.07.17)-2",
    "url": "https://blog.naver.com/universalfather0/224349202221",
    "sources": [
      "네이버블로그",
      "네이버카페",
      "더쿠",
      "뽐뿌"
    ],
    "source_count": 4,
    "platform_count": 3,
    "posts": 34,
    "src_posts": {
      "더쿠": 2,
      "뽐뿌": 1,
      "네이버카페": 29,
      "네이버블로그": 2
    },
    "age_h": 0.9,
    "burst": 14.88
  },
  {
    "title": "김민석, 학폭 피해자 항의 무마 의혹…\"공천은 당의 결정\"",
    "url": "https://www.issuelink.co.kr/community/go/todayhumor/15619430",
    "sources": [
      "네이버카페",
      "오유"
    ],
    "source_count": 2,
    "platform_count": 2,
    "posts": 7,
    "src_posts": {
      "오유": 1,
      "네이버카페": 6
    },
    "age_h": 2.4,
    "burst": 10.24
  },
  {
    "title": "알리바바가 미국 AI 클로드를 그대로 베끼는 방법",
    "url": "https://www.issuelink.co.kr/community/go/fmkorea/10110836066",
    "sources": [
      "더쿠",
      "에펨코리아"
    ],
    "source_count": 2,
    "platform_count": 2,
    "posts": 2,
    "src_posts": {
      "더쿠": 1,
      "에펨코리아": 1
    },
    "age_h": 0.8,
    "burst": 10.07
  },
  {
    "title": "넷플릭스 동궁 (한국판 콘스탄틴, 데빌메이크라이) + 천녀유혼 홍콩",
    "url": "https://www.issuelink.co.kr/community/go/clien/19231436",
    "sources": [
      "뽐뿌",
      "클리앙"
    ],
    "source_count": 2,
    "platform_count": 2,
    "posts": 2,
    "src_posts": {
      "클리앙": 1,
      "뽐뿌": 1
    },
    "age_h": 0.9,
    "burst": 10.06
  },
  {
    "title": "영화 하우스메이드 정보!  줄거리 결말 해석  \"완벽한 저택에...",
    "url": "https://blog.naver.com/ilovemovie12/224347817567",
    "sources": [
      "네이버블로그",
      "더쿠"
    ],
    "source_count": 2,
    "platform_count": 2,
    "posts": 2,
    "src_posts": {
      "더쿠": 1,
      "네이버블로그": 1
    },
    "age_h": 1.0,
    "burst": 9.93
  },
  {
    "title": "31살에 2천억 벌고 은퇴.jpg",
    "url": "https://www.issuelink.co.kr/community/go/etoland/9199539",
    "sources": [
      "이토랜드",
      "인스티즈"
    ],
    "source_count": 2,
    "platform_count": 2,
    "posts": 2,
    "src_posts": {
      "이토랜드": 1,
      "인스티즈": 1
    },
    "age_h": 2.4,
    "burst": 9.87
  },
  {
    "title": "23.1% ‘김부장’, SBS 연기 대상 트로피에 벌써 소지섭 이름 새겼나 [돌파구]",
    "url": "https://www.issuelink.co.kr/community/go/theqoo/4286461897",
    "sources": [
      "네이버카페",
      "더쿠"
    ],
    "source_count": 2,
    "platform_count": 2,
    "posts": 2,
    "src_posts": {
      "더쿠": 1,
      "네이버카페": 1
    },
    "age_h": 1.8,
    "burst": 9.1
  },
  {
    "title": "쿠팡... 로비할 땐 미국 기업, 미국 내 소송에선 한국 기업?",
    "url": "https://www.issuelink.co.kr/community/go/clien/19231417",
    "sources": [
      "네이버카페",
      "클리앙"
    ],
    "source_count": 2,
    "platform_count": 2,
    "posts": 2,
    "src_posts": {
      "클리앙": 1,
      "네이버카페": 1
    },
    "age_h": 3.0,
    "burst": 8.94
  }
]