{"as_of":"2026-07-13T07:53+09:00","window_h":24,"totals":{"all":{"calls":239,"in":468,"out":563028,"cache_r":4002066,"cache_w":3444828,"cost":43.818768399999996,"dur_ms":8480919},"by_src":{"breaking":{"calls":72,"in":144,"out":12666,"cache_r":1075943,"cache_w":628611,"cost":4.6468949,"dur_ms":331785},"gate":{"calls":82,"in":164,"out":165805,"cache_r":1201965,"cache_w":727736,"cost":7.633270499999998,"dur_ms":2427664},"group":{"calls":61,"in":122,"out":27553,"cache_r":693970,"cache_w":332502,"cost":4.467425999999999,"dur_ms":642531},"analyze":{"calls":5,"in":14,"out":36347,"cache_r":795052,"cache_w":283009,"cost":4.207364,"dur_ms":575141},"card":{"calls":13,"in":12,"out":289105,"cache_r":75330,"cache_w":1025842,"cost":17.52377,"dur_ms":4112867},"autopick":{"calls":3,"in":6,"out":862,"cache_r":35895,"cache_w":255944,"cost":2.5989675,"dur_ms":27166},"ly":{"calls":1,"in":4,"out":25634,"cache_r":111946,"cache_w":105408,"cost":1.750923,"dur_ms":297919},"k":{"calls":1,"in":0,"out":0,"cache_r":0,"cache_w":0,"cost":0.0,"dur_ms":1158},"song-lyria":{"calls":1,"in":2,"out":5056,"cache_r":11965,"cache_w":85776,"cost":0.9901525000000001,"dur_ms":64688}}},"buckets":[{"t":"07-12 08:00","iso":"2026-07-12T08:00+09:00","by_src":{"breaking":{"calls":1,"in":2,"out":6,"cache_r":14946,"cache_w":8744,"cost":0.0622968,"dur_ms":2309},"gate":{"calls":1,"in":2,"out":1544,"cache_r":14946,"cache_w":8573,"cost":0.0841558,"dur_ms":23275}},"tok":1554,"calls":2},{"t":"07-12 08:20","iso":"2026-07-12T08:20+09:00","by_src":{"breaking":{"calls":1,"in":2,"out":16,"cache_r":14946,"cache_w":8745,"cost":0.06253979999999999,"dur_ms":2272},"gate":{"calls":1,"in":2,"out":4806,"cache_r":14946,"cache_w":9054,"cost":0.1364978,"dur_ms":67773},"group":{"calls":1,"in":2,"out":702,"cache_r":11965,"cache_w":4874,"cost":0.0741375,"dur_ms":13035}},"tok":5530,"calls":3},{"t":"07-12 08:30","iso":"2026-07-12T08:30+09:00","by_src":{"breaking":{"calls":1,"in":2,"out":21,"cache_r":14946,"cache_w":8814,"cost":0.0630838,"dur_ms":1628},"gate":{"calls":1,"in":2,"out":1524,"cache_r":14946,"cache_w":8262,"cost":0.0817768,"dur_ms":21876},"group":{"calls":1,"in":2,"out":983,"cache_r":11965,"cache_w":4907,"cost":0.0815365,"dur_ms":20563}},"tok":2534,"calls":3},{"t":"07-12 08:50","iso":"2026-07-12T08:50+09:00","by_src":{"breaking":{"calls":1,"in":2,"out":16,"cache_r":14946,"cache_w":8545,"cost":0.0613258,"dur_ms":2510},"gate":{"calls":1,"in":2,"out":3267,"cache_r":14946,"cache_w":8741,"cost":0.1114058,"dur_ms":45431},"group":{"calls":1,"in":2,"out":553,"cache_r":11965,"cache_w":4529,"cost":0.0666245,"dur_ms":12831}},"tok":3842,"calls":3},{"t":"07-12 09:00","iso":"2026-07-12T09:00+09:00","by_src":{"breaking":{"calls":1,"in":2,"out":416,"cache_r":14946,"cache_w":8968,"cost":0.07008080000000001,"dur_ms":7345},"gate":{"calls":1,"in":2,"out":4912,"cache_r":14946,"cache_w":9764,"cost":0.14299179999999997,"dur_ms":67705},"group":{"calls":1,"in":2,"out":779,"cache_r":11965,"cache_w":5225,"cost":0.07968349999999999,"dur_ms":13226}},"tok":6113,"calls":3},{"t":"07-12 09:20","iso":"2026-07-12T09:20+09:00","by_src":{"breaking":{"calls":1,"in":2,"out":6,"cache_r":14946,"cache_w":8508,"cost":0.0608818,"dur_ms":2428},"gate":{"calls":1,"in":2,"out":3315,"cache_r":14946,"cache_w":8655,"cost":0.11150679999999999,"dur_ms":49959},"group":{"calls":1,"in":2,"out":208,"cache_r":11965,"cache_w":4635,"cost":0.059090500000000004,"dur_ms":5151}},"tok":3535,"calls":3},{"t":"07-12 09:30","iso":"2026-07-12T09:30+09:00","by_src":{"breaking":{"calls":1,"in":2,"out":11,"cache_r":14946,"cache_w":8592,"cost":0.0614628,"dur_ms":2357},"gate":{"calls":1,"in":2,"out":1935,"cache_r":14946,"cache_w":8455,"cost":0.08928080000000001,"dur_ms":28341},"group":{"calls":1,"in":2,"out":219,"cache_r":11965,"cache_w":4977,"cost":0.0631105,"dur_ms":5931}},"tok":2171,"calls":3},{"t":"07-12 09:50","iso":"2026-07-12T09:50+09:00","by_src":{"breaking":{"calls":1,"in":2,"out":6,"cache_r":14946,"cache_w":8549,"cost":0.0611218,"dur_ms":2633},"gate":{"calls":1,"in":2,"out":1715,"cache_r":14946,"cache_w":8335,"cost":0.0852368,"dur_ms":31094},"group":{"calls":1,"in":2,"out":900,"cache_r":11965,"cache_w":4786,"cost":0.07804649999999999,"dur_ms":18685}},"tok":2627,"calls":3},{"t":"07-12 10:00","iso":"2026-07-12T10:00+09:00","by_src":{"breaking":{"calls":1,"in":2,"out":385,"cache_r":14946,"cache_w":8902,"cost":0.06907780000000001,"dur_ms":7647},"gate":{"calls":1,"in":2,"out":148,"cache_r":14946,"cache_w":8831,"cost":0.06499780000000001,"dur_ms":2407},"group":{"calls":1,"in":2,"out":1275,"cache_r":11965,"cache_w":4914,"cost":0.08882350000000001,"dur_ms":24354}},"tok":1814,"calls":3},{"t":"07-12 10:10","iso":"2026-07-12T10:10+09:00","by_src":{"analyze":{"calls":1,"in":6,"out":19081,"cache_r":314950,"cache_w":139211,"cost":2.073019,"dur_ms":297143}},"tok":19087,"calls":1},{"t":"07-12 10:20","iso":"2026-07-12T10:20+09:00","by_src":{"breaking":{"calls":1,"in":2,"out":6,"cache_r":14946,"cache_w":8522,"cost":0.0609668,"dur_ms":1950},"gate":{"calls":1,"in":2,"out":2634,"cache_r":14946,"cache_w":8540,"cost":0.10049180000000002,"dur_ms":38148},"group":{"calls":1,"in":2,"out":160,"cache_r":11965,"cache_w":4660,"cost":0.0581935,"dur_ms":4462}},"tok":2806,"calls":3},{"t":"07-12 10:40","iso":"2026-07-12T10:40+09:00","by_src":{"card":{"calls":1,"in":4,"out":106679,"cache_r":25707,"cache_w":340178,"cost":6.081628500000001,"dur_ms":1495626},"breaking":{"calls":1,"in":2,"out":6,"cache_r":14946,"cache_w":8552,"cost":0.061144800000000006,"dur_ms":2755},"gate":{"calls":1,"in":2,"out":3842,"cache_r":14946,"cache_w":9244,"cost":0.1234648,"dur_ms":56367},"group":{"calls":1,"in":2,"out":382,"cache_r":11965,"cache_w":5103,"cost":0.0685795,"dur_ms":8104}},"tok":110919,"calls":4},{"t":"07-12 10:50","iso":"2026-07-12T10:50+09:00","by_src":{"card":{"calls":1,"in":2,"out":39915,"cache_r":11965,"cache_w":171215,"cost":2.7160175,"dur_ms":625285},"breaking":{"calls":1,"in":2,"out":21,"cache_r":14946,"cache_w":8715,"cost":0.0625238,"dur_ms":3064},"gate":{"calls":1,"in":2,"out":3219,"cache_r":14946,"cache_w":8485,"cost":0.1088478,"dur_ms":47600},"group":{"calls":1,"in":2,"out":577,"cache_r":11965,"cache_w":5257,"cost":0.0751325,"dur_ms":13164}},"tok":43740,"calls":4},{"t":"07-12 11:00","iso":"2026-07-12T11:00+09:00","by_src":{"breaking":{"calls":1,"in":2,"out":36,"cache_r":14946,"cache_w":8900,"cost":0.06391580000000001,"dur_ms":2397},"gate":{"calls":1,"in":2,"out":5981,"cache_r":14946,"cache_w":9679,"cost":0.1584698,"dur_ms":81883},"group":{"calls":1,"in":2,"out":905,"cache_r":11965,"cache_w":5033,"cost":0.0807665,"dur_ms":20509}},"tok":6928,"calls":3},{"t":"07-12 11:20","iso":"2026-07-12T11:20+09:00","by_src":{"breaking":{"calls":1,"in":2,"out":821,"cache_r":14946,"cache_w":8985,"cost":0.07627279999999999,"dur_ms":12452},"gate":{"calls":1,"in":2,"out":2715,"cache_r":14946,"cache_w":9099,"cost":0.10547580000000001,"dur_ms":37907},"group":{"calls":1,"in":2,"out":568,"cache_r":11965,"cache_w":5194,"cost":0.0742875,"dur_ms":13181},"autopick":{"calls":1,"in":2,"out":528,"cache_r":11965,"cache_w":82299,"cost":0.8421825000000001,"dur_ms":12323}},"tok":4640,"calls":4},{"t":"07-12 11:30","iso":"2026-07-12T11:30+09:00","by_src":{"card":{"calls":1,"in":2,"out":45144,"cache_r":11965,"cache_w":171851,"cost":2.8531025,"dur_ms":660050},"ly":{"calls":1,"in":4,"out":25634,"cache_r":111946,"cache_w":105408,"cost":1.750923,"dur_ms":297919},"breaking":{"calls":1,"in":2,"out":523,"cache_r":14777,"cache_w":9159,"cost":0.07296110000000001,"dur_ms":8341},"gate":{"calls":1,"in":2,"out":3695,"cache_r":14777,"cache_w":8827,"cost":0.1182161,"dur_ms":50413},"group":{"calls":1,"in":2,"out":958,"cache_r":0,"cache_w":17181,"cost":0.198034,"dur_ms":22686}},"tok":75966,"calls":5},{"t":"07-12 11:50","iso":"2026-07-12T11:50+09:00","by_src":{"card":{"calls":4,"in":4,"out":97367,"cache_r":25693,"cache_w":342598,"cost":5.8730215,"dur_ms":1329213},"analyze":{"calls":1,"in":0,"out":0,"cache_r":0,"cache_w":0,"cost":0.0,"dur_ms":1032},"breaking":{"calls":1,"in":2,"out":1349,"cache_r":14946,"cache_w":8828,"cost":0.0832388,"dur_ms":20090},"gate":{"calls":2,"in":4,"out":5840,"cache_r":31170,"cache_w":16392,"cost":0.206309,"dur_ms":83704},"group":{"calls":1,"in":2,"out":1470,"cache_r":11965,"cache_w":4854,"cost":0.0931015,"dur_ms":26257}},"tok":106038,"calls":9},{"t":"07-12 12:50","iso":"2026-07-12T12:50+09:00","by_src":{"analyze":{"calls":1,"in":0,"out":0,"cache_r":0,"cache_w":0,"cost":0.0,"dur_ms":652},"card":{"calls":3,"in":0,"out":0,"cache_r":0,"cache_w":0,"cost":0.0,"dur_ms":979},"k":{"calls":1,"in":0,"out":0,"cache_r":0,"cache_w":0,"cost":0.0,"dur_ms":1158}},"tok":0,"calls":5},{"t":"07-12 13:50","iso":"2026-07-12T13:50+09:00","by_src":{"analyze":{"calls":1,"in":0,"out":0,"cache_r":0,"cache_w":0,"cost":0.0,"dur_ms":1158},"card":{"calls":3,"in":0,"out":0,"cache_r":0,"cache_w":0,"cost":0.0,"dur_ms":1714}},"tok":0,"calls":4},{"t":"07-12 17:00","iso":"2026-07-12T17:00+09:00","by_src":{"breaking":{"calls":1,"in":2,"out":824,"cache_r":14946,"cache_w":9511,"cost":0.0799938,"dur_ms":13540},"gate":{"calls":1,"in":2,"out":6589,"cache_r":14946,"cache_w":9556,"cost":0.16675879999999998,"dur_ms":92970}},"tok":7417,"calls":2},{"t":"07-12 17:10","iso":"2026-07-12T17:10+09:00","by_src":{"gate":{"calls":4,"in":8,"out":24221,"cache_r":63679,"cache_w":34411,"cost":0.6137637,"dur_ms":329974},"group":{"calls":1,"in":2,"out":3152,"cache_r":11965,"cache_w":6956,"cost":0.1582335,"dur_ms":54833}},"tok":27383,"calls":5},{"t":"07-12 17:20","iso":"2026-07-12T17:20+09:00","by_src":{"gate":{"calls":1,"in":2,"out":2350,"cache_r":14946,"cache_w":8746,"cost":0.09749080000000002,"dur_ms":32233},"group":{"calls":1,"in":2,"out":575,"cache_r":11965,"cache_w":5312,"cost":0.0755565,"dur_ms":11609}},"tok":2929,"calls":2},{"t":"07-12 17:30","iso":"2026-07-12T17:30+09:00","by_src":{"breaking":{"calls":1,"in":2,"out":804,"cache_r":14946,"cache_w":8826,"cost":0.0750258,"dur_ms":13179},"gate":{"calls":1,"in":2,"out":3823,"cache_r":14946,"cache_w":8904,"cost":0.1208358,"dur_ms":55007},"group":{"calls":1,"in":2,"out":283,"cache_r":11965,"cache_w":4570,"cost":0.060283500000000004,"dur_ms":7803}},"tok":4916,"calls":3},{"t":"07-12 17:50","iso":"2026-07-12T17:50+09:00","by_src":{"breaking":{"calls":1,"in":2,"out":145,"cache_r":14946,"cache_w":8645,"cost":0.06387179999999999,"dur_ms":3436},"gate":{"calls":1,"in":2,"out":1677,"cache_r":14946,"cache_w":8862,"cost":0.0883288,"dur_ms":25343},"group":{"calls":1,"in":2,"out":122,"cache_r":11965,"cache_w":4680,"cost":0.057432500000000004,"dur_ms":4097}},"tok":1950,"calls":3},{"t":"07-12 18:00","iso":"2026-07-12T18:00+09:00","by_src":{"breaking":{"calls":1,"in":2,"out":771,"cache_r":14946,"cache_w":9225,"cost":0.0773118,"dur_ms":13077},"gate":{"calls":1,"in":2,"out":2577,"cache_r":14946,"cache_w":9176,"cost":0.1040148,"dur_ms":38860},"group":{"calls":1,"in":2,"out":1065,"cache_r":11965,"cache_w":4930,"cost":0.08375250000000001,"dur_ms":21360}},"tok":4419,"calls":3},{"t":"07-12 18:20","iso":"2026-07-12T18:20+09:00","by_src":{"breaking":{"calls":1,"in":2,"out":242,"cache_r":14946,"cache_w":8859,"cost":0.0666448,"dur_ms":5415},"gate":{"calls":1,"in":2,"out":85,"cache_r":14946,"cache_w":8439,"cost":0.0612868,"dur_ms":2382}},"tok":331,"calls":2},{"t":"07-12 18:30","iso":"2026-07-12T18:30+09:00","by_src":{"breaking":{"calls":1,"in":2,"out":11,"cache_r":14946,"cache_w":8688,"cost":0.06204779999999999,"dur_ms":1723},"gate":{"calls":1,"in":2,"out":85,"cache_r":14946,"cache_w":8326,"cost":0.0605638,"dur_ms":2765},"group":{"calls":1,"in":2,"out":19,"cache_r":11965,"cache_w":4703,"cost":0.055190499999999997,"dur_ms":4370}},"tok":121,"calls":3},{"t":"07-12 18:50","iso":"2026-07-12T18:50+09:00","by_src":{"breaking":{"calls":1,"in":2,"out":6,"cache_r":14946,"cache_w":8529,"cost":0.0610118,"dur_ms":1922},"gate":{"calls":1,"in":2,"out":1238,"cache_r":14946,"cache_w":8190,"cost":0.0770328,"dur_ms":18117}},"tok":1248,"calls":2},{"t":"07-12 19:00","iso":"2026-07-12T19:00+09:00","by_src":{"breaking":{"calls":1,"in":2,"out":16,"cache_r":14946,"cache_w":8600,"cost":0.0563298,"dur_ms":1725}},"tok":18,"calls":1},{"t":"07-12 19:10","iso":"2026-07-12T19:10+09:00","by_src":{"gate":{"calls":1,"in":2,"out":2731,"cache_r":14946,"cache_w":8511,"cost":0.1017358,"dur_ms":38291},"group":{"calls":1,"in":2,"out":507,"cache_r":11965,"cache_w":4883,"cost":0.06931349999999999,"dur_ms":11698}},"tok":3242,"calls":2},{"t":"07-12 19:20","iso":"2026-07-12T19:20+09:00","by_src":{"breaking":{"calls":1,"in":2,"out":633,"cache_r":14946,"cache_w":8870,"cost":0.0725888,"dur_ms":10240},"gate":{"calls":1,"in":2,"out":2809,"cache_r":14946,"cache_w":9110,"cost":0.10687079999999999,"dur_ms":37402},"group":{"calls":1,"in":2,"out":469,"cache_r":11965,"cache_w":4796,"cost":0.0673795,"dur_ms":10826}},"tok":3917,"calls":3},{"t":"07-12 19:30","iso":"2026-07-12T19:30+09:00","by_src":{"breaking":{"calls":1,"in":2,"out":11,"cache_r":14946,"cache_w":8584,"cost":0.061453799999999996,"dur_ms":2392},"gate":{"calls":1,"in":2,"out":92,"cache_r":14946,"cache_w":8367,"cost":0.061112799999999995,"dur_ms":4719},"group":{"calls":1,"in":2,"out":149,"cache_r":11965,"cache_w":4934,"cost":0.0607145,"dur_ms":4708}},"tok":258,"calls":3},{"t":"07-12 19:50","iso":"2026-07-12T19:50+09:00","by_src":{"breaking":{"calls":1,"in":2,"out":538,"cache_r":14946,"cache_w":8822,"cost":0.0710558,"dur_ms":9417},"gate":{"calls":1,"in":2,"out":3250,"cache_r":14946,"cache_w":8489,"cost":0.10938179999999999,"dur_ms":44952},"group":{"calls":1,"in":2,"out":124,"cache_r":11965,"cache_w":4875,"cost":0.059507500000000005,"dur_ms":4370}},"tok":3918,"calls":3},{"t":"07-12 20:00","iso":"2026-07-12T20:00+09:00","by_src":{"breaking":{"calls":1,"in":2,"out":61,"cache_r":14946,"cache_w":9225,"cost":0.0664788,"dur_ms":2907},"gate":{"calls":1,"in":2,"out":127,"cache_r":14946,"cache_w":8758,"cost":0.0642008,"dur_ms":5456}},"tok":192,"calls":2},{"t":"07-12 20:10","iso":"2026-07-12T20:10+09:00","by_src":{"group":{"calls":1,"in":2,"out":543,"cache_r":11965,"cache_w":5004,"cost":0.0715085,"dur_ms":13245}},"tok":545,"calls":1},{"t":"07-12 20:20","iso":"2026-07-12T20:20+09:00","by_src":{"breaking":{"calls":1,"in":2,"out":6,"cache_r":14946,"cache_w":8467,"cost":0.0606248,"dur_ms":3114},"gate":{"calls":1,"in":2,"out":71,"cache_r":14946,"cache_w":8033,"cost":0.058540800000000004,"dur_ms":3477},"group":{"calls":1,"in":2,"out":156,"cache_r":11965,"cache_w":4407,"cost":0.055371500000000004,"dur_ms":5286}},"tok":239,"calls":3},{"t":"07-12 20:30","iso":"2026-07-12T20:30+09:00","by_src":{"breaking":{"calls":1,"in":2,"out":11,"cache_r":14946,"cache_w":8536,"cost":0.061182799999999996,"dur_ms":2354},"gate":{"calls":1,"in":2,"out":1091,"cache_r":14946,"cache_w":8090,"cost":0.0742418,"dur_ms":18415},"group":{"calls":1,"in":2,"out":936,"cache_r":11965,"cache_w":5110,"cost":0.08255549999999999,"dur_ms":16886}},"tok":2044,"calls":3},{"t":"07-12 20:40","iso":"2026-07-12T20:40+09:00","by_src":{"song-lyria":{"calls":1,"in":2,"out":5056,"cache_r":11965,"cache_w":85776,"cost":0.9901525000000001,"dur_ms":64688}},"tok":5058,"calls":1},{"t":"07-12 20:50","iso":"2026-07-12T20:50+09:00","by_src":{"breaking":{"calls":1,"in":2,"out":21,"cache_r":14946,"cache_w":8673,"cost":0.0622278,"dur_ms":2484},"gate":{"calls":1,"in":2,"out":1691,"cache_r":14946,"cache_w":8235,"cost":0.0841228,"dur_ms":26680}},"tok":1716,"calls":2},{"t":"07-12 21:00","iso":"2026-07-12T21:00+09:00","by_src":{"breaking":{"calls":1,"in":2,"out":46,"cache_r":14946,"cache_w":9121,"cost":0.0654988,"dur_ms":2512},"gate":{"calls":1,"in":2,"out":3901,"cache_r":14946,"cache_w":9245,"cost":0.12407679999999999,"dur_ms":50695},"group":{"calls":1,"in":2,"out":342,"cache_r":11965,"cache_w":5095,"cost":0.0672835,"dur_ms":9135}},"tok":4295,"calls":3},{"t":"07-12 21:20","iso":"2026-07-12T21:20+09:00","by_src":{"breaking":{"calls":1,"in":2,"out":151,"cache_r":14946,"cache_w":8697,"cost":0.0643218,"dur_ms":3115},"gate":{"calls":1,"in":2,"out":880,"cache_r":14946,"cache_w":8256,"cost":0.0721548,"dur_ms":13587},"group":{"calls":1,"in":2,"out":7,"cache_r":11965,"cache_w":4586,"cost":0.0535545,"dur_ms":5436}},"tok":1044,"calls":3},{"t":"07-12 21:30","iso":"2026-07-12T21:30+09:00","by_src":{"breaking":{"calls":1,"in":2,"out":46,"cache_r":14946,"cache_w":8935,"cost":0.06440080000000001,"dur_ms":2893},"gate":{"calls":1,"in":2,"out":2211,"cache_r":14946,"cache_w":8712,"cost":0.0952118,"dur_ms":31746},"group":{"calls":1,"in":2,"out":94,"cache_r":11965,"cache_w":4608,"cost":0.0559195,"dur_ms":6926}},"tok":2357,"calls":3},{"t":"07-12 21:50","iso":"2026-07-12T21:50+09:00","by_src":{"breaking":{"calls":1,"in":2,"out":16,"cache_r":14946,"cache_w":8842,"cost":0.0631098,"dur_ms":2724},"gate":{"calls":1,"in":2,"out":78,"cache_r":14946,"cache_w":8511,"cost":0.0616358,"dur_ms":3367},"group":{"calls":1,"in":2,"out":256,"cache_r":11965,"cache_w":4994,"cost":0.0640035,"dur_ms":6534}},"tok":356,"calls":3},{"t":"07-12 22:00","iso":"2026-07-12T22:00+09:00","by_src":{"breaking":{"calls":1,"in":2,"out":21,"cache_r":14946,"cache_w":8686,"cost":0.062320799999999996,"dur_ms":2380},"gate":{"calls":1,"in":2,"out":120,"cache_r":14946,"cache_w":8467,"cost":0.0622248,"dur_ms":4374},"group":{"calls":1,"in":2,"out":109,"cache_r":11965,"cache_w":4659,"cost":0.056874499999999995,"dur_ms":4269}},"tok":256,"calls":3},{"t":"07-12 22:20","iso":"2026-07-12T22:20+09:00","by_src":{"breaking":{"calls":1,"in":2,"out":46,"cache_r":14946,"cache_w":8895,"cost":0.0641478,"dur_ms":2852},"gate":{"calls":1,"in":2,"out":99,"cache_r":14946,"cache_w":8413,"cost":0.06153380000000001,"dur_ms":3288},"group":{"calls":1,"in":2,"out":454,"cache_r":11965,"cache_w":4909,"cost":0.06825650000000001,"dur_ms":9673}},"tok":605,"calls":3},{"t":"07-12 22:30","iso":"2026-07-12T22:30+09:00","by_src":{"breaking":{"calls":1,"in":2,"out":16,"cache_r":14946,"cache_w":8598,"cost":0.061613799999999996,"dur_ms":2818},"gate":{"calls":1,"in":2,"out":2185,"cache_r":14946,"cache_w":8879,"cost":0.09609580000000001,"dur_ms":33764},"group":{"calls":1,"in":2,"out":122,"cache_r":11965,"cache_w":4805,"cost":0.05881550000000001,"dur_ms":3835}},"tok":2329,"calls":3},{"t":"07-12 22:50","iso":"2026-07-12T22:50+09:00","by_src":{"breaking":{"calls":1,"in":2,"out":21,"cache_r":14946,"cache_w":8637,"cost":0.0620368,"dur_ms":2235},"gate":{"calls":1,"in":2,"out":85,"cache_r":14946,"cache_w":8259,"cost":0.0553188,"dur_ms":2560},"group":{"calls":1,"in":2,"out":200,"cache_r":11965,"cache_w":4688,"cost":0.059333500000000004,"dur_ms":6318}},"tok":312,"calls":3},{"t":"07-12 23:00","iso":"2026-07-12T23:00+09:00","by_src":{"gate":{"calls":1,"in":2,"out":2031,"cache_r":16227,"cache_w":7157,"cost":0.08341309999999999,"dur_ms":34924},"group":{"calls":1,"in":2,"out":168,"cache_r":11965,"cache_w":4995,"cost":0.0618835,"dur_ms":6213}},"tok":2203,"calls":2},{"t":"07-12 23:20","iso":"2026-07-12T23:20+09:00","by_src":{"breaking":{"calls":1,"in":2,"out":227,"cache_r":14946,"cache_w":8833,"cost":0.06643980000000001,"dur_ms":5414},"gate":{"calls":1,"in":2,"out":1047,"cache_r":14946,"cache_w":8443,"cost":0.07597480000000001,"dur_ms":15976},"group":{"calls":1,"in":2,"out":957,"cache_r":11965,"cache_w":5203,"cost":0.0840665,"dur_ms":21507}},"tok":2237,"calls":3},{"t":"07-12 23:30","iso":"2026-07-12T23:30+09:00","by_src":{"breaking":{"calls":1,"in":2,"out":6,"cache_r":14946,"cache_w":8573,"cost":0.061261800000000005,"dur_ms":4417},"gate":{"calls":1,"in":2,"out":985,"cache_r":14946,"cache_w":8451,"cost":0.0750338,"dur_ms":17616},"group":{"calls":1,"in":2,"out":169,"cache_r":11965,"cache_w":4877,"cost":0.0607455,"dur_ms":5075}},"tok":1166,"calls":3},{"t":"07-12 23:50","iso":"2026-07-12T23:50+09:00","by_src":{"breaking":{"calls":1,"in":2,"out":31,"cache_r":14946,"cache_w":8775,"cost":0.0630728,"dur_ms":2832},"gate":{"calls":1,"in":2,"out":1381,"cache_r":14946,"cache_w":8483,"cost":0.0812438,"dur_ms":23072},"group":{"calls":1,"in":2,"out":98,"cache_r":11965,"cache_w":4575,"cost":0.0556875,"dur_ms":8164}},"tok":1516,"calls":3},{"t":"07-13 00:00","iso":"2026-07-13T00:00+09:00","by_src":{"breaking":{"calls":1,"in":2,"out":21,"cache_r":14946,"cache_w":8636,"cost":0.0620058,"dur_ms":2765},"gate":{"calls":1,"in":2,"out":1623,"cache_r":14946,"cache_w":8651,"cost":0.0860838,"dur_ms":24926},"group":{"calls":1,"in":2,"out":738,"cache_r":11965,"cache_w":4936,"cost":0.0754985,"dur_ms":14929}},"tok":2388,"calls":3},{"t":"07-13 00:20","iso":"2026-07-13T00:20+09:00","by_src":{"breaking":{"calls":1,"in":2,"out":16,"cache_r":14946,"cache_w":8613,"cost":0.061766800000000004,"dur_ms":1762},"gate":{"calls":1,"in":2,"out":36,"cache_r":14946,"cache_w":7969,"cost":0.0574578,"dur_ms":2321}},"tok":56,"calls":2},{"t":"07-13 00:30","iso":"2026-07-13T00:30+09:00","by_src":{"breaking":{"calls":1,"in":2,"out":242,"cache_r":14946,"cache_w":9057,"cost":0.0624618,"dur_ms":5087},"gate":{"calls":1,"in":2,"out":1503,"cache_r":14946,"cache_w":8702,"cost":0.0845078,"dur_ms":21389}},"tok":1749,"calls":2},{"t":"07-13 00:50","iso":"2026-07-13T00:50+09:00","by_src":{"breaking":{"calls":1,"in":2,"out":21,"cache_r":14946,"cache_w":8653,"cost":0.06207079999999999,"dur_ms":2191},"gate":{"calls":1,"in":2,"out":922,"cache_r":14946,"cache_w":8201,"cost":0.0723868,"dur_ms":15191}},"tok":947,"calls":2},{"t":"07-13 01:00","iso":"2026-07-13T01:00+09:00","by_src":{"gate":{"calls":1,"in":2,"out":1913,"cache_r":0,"cache_w":22897,"cost":0.170942,"dur_ms":26113},"group":{"calls":1,"in":2,"out":426,"cache_r":0,"cache_w":16330,"cost":0.17544400000000002,"dur_ms":10193}},"tok":2343,"calls":2},{"t":"07-13 01:20","iso":"2026-07-13T01:20+09:00","by_src":{"breaking":{"calls":1,"in":2,"out":362,"cache_r":14946,"cache_w":8897,"cost":0.0688568,"dur_ms":8316},"gate":{"calls":1,"in":2,"out":2136,"cache_r":14946,"cache_w":8817,"cost":0.0948658,"dur_ms":35867},"group":{"calls":1,"in":2,"out":191,"cache_r":11965,"cache_w":4877,"cost":0.0611335,"dur_ms":5217}},"tok":2695,"calls":3},{"t":"07-13 01:30","iso":"2026-07-13T01:30+09:00","by_src":{"breaking":{"calls":1,"in":2,"out":361,"cache_r":14946,"cache_w":8969,"cost":0.0693848,"dur_ms":7062},"gate":{"calls":1,"in":2,"out":1202,"cache_r":14946,"cache_w":8466,"cost":0.07847679999999999,"dur_ms":17777}},"tok":1567,"calls":2},{"t":"07-13 01:50","iso":"2026-07-13T01:50+09:00","by_src":{"breaking":{"calls":1,"in":2,"out":11,"cache_r":14946,"cache_w":8482,"cost":0.0608148,"dur_ms":2001},"gate":{"calls":1,"in":2,"out":43,"cache_r":14946,"cache_w":7953,"cost":0.0575768,"dur_ms":2361},"group":{"calls":1,"in":2,"out":7,"cache_r":11965,"cache_w":4632,"cost":0.0539185,"dur_ms":2488}},"tok":67,"calls":3},{"t":"07-13 02:00","iso":"2026-07-13T02:00+09:00","by_src":{"breaking":{"calls":1,"in":2,"out":11,"cache_r":14946,"cache_w":8849,"cost":0.0630698,"dur_ms":2435},"gate":{"calls":1,"in":2,"out":1773,"cache_r":14946,"cache_w":8716,"cost":0.0885358,"dur_ms":25041}},"tok":1788,"calls":2},{"t":"07-13 02:20","iso":"2026-07-13T02:20+09:00","by_src":{"breaking":{"calls":1,"in":2,"out":6,"cache_r":14946,"cache_w":8713,"cost":0.062088800000000006,"dur_ms":2557},"gate":{"calls":1,"in":2,"out":760,"cache_r":14946,"cache_w":8345,"cost":0.07098480000000001,"dur_ms":12444}},"tok":770,"calls":2},{"t":"07-13 02:30","iso":"2026-07-13T02:30+09:00","by_src":{"breaking":{"calls":1,"in":2,"out":92,"cache_r":14946,"cache_w":8639,"cost":0.0630618,"dur_ms":2866},"gate":{"calls":1,"in":2,"out":439,"cache_r":14946,"cache_w":8106,"cost":0.0645438,"dur_ms":7464},"group":{"calls":1,"in":2,"out":147,"cache_r":11965,"cache_w":4886,"cost":0.06018249999999999,"dur_ms":7826}},"tok":684,"calls":3},{"t":"07-13 02:50","iso":"2026-07-13T02:50+09:00","by_src":{"breaking":{"calls":1,"in":2,"out":244,"cache_r":14946,"cache_w":8673,"cost":0.0601878,"dur_ms":5545},"gate":{"calls":1,"in":2,"out":1949,"cache_r":14946,"cache_w":8485,"cost":0.0896638,"dur_ms":26569},"group":{"calls":1,"in":2,"out":7,"cache_r":11965,"cache_w":4418,"cost":0.050347499999999996,"dur_ms":3075}},"tok":2206,"calls":3},{"t":"07-13 03:00","iso":"2026-07-13T03:00+09:00","by_src":{"breaking":{"calls":1,"in":2,"out":972,"cache_r":14946,"cache_w":8863,"cost":0.0778168,"dur_ms":15935},"gate":{"calls":1,"in":2,"out":2067,"cache_r":14946,"cache_w":8664,"cost":0.0927368,"dur_ms":30690},"group":{"calls":1,"in":2,"out":651,"cache_r":11965,"cache_w":5605,"cost":0.0806515,"dur_ms":13191}},"tok":3696,"calls":3},{"t":"07-13 03:20","iso":"2026-07-13T03:20+09:00","by_src":{"gate":{"calls":1,"in":2,"out":29,"cache_r":0,"cache_w":22806,"cost":0.137277,"dur_ms":2355},"group":{"calls":1,"in":2,"out":146,"cache_r":0,"cache_w":16703,"cost":0.172366,"dur_ms":8671}},"tok":179,"calls":2},{"t":"07-13 03:30","iso":"2026-07-13T03:30+09:00","by_src":{"breaking":{"calls":1,"in":2,"out":11,"cache_r":14946,"cache_w":8505,"cost":0.06097380000000001,"dur_ms":2311},"gate":{"calls":1,"in":2,"out":29,"cache_r":14946,"cache_w":7827,"cost":0.0564718,"dur_ms":2832},"group":{"calls":1,"in":2,"out":481,"cache_r":11965,"cache_w":4766,"cost":0.0674275,"dur_ms":11847}},"tok":527,"calls":3},{"t":"07-13 03:50","iso":"2026-07-13T03:50+09:00","by_src":{"breaking":{"calls":1,"in":2,"out":6,"cache_r":14946,"cache_w":8526,"cost":0.06101780000000001,"dur_ms":3887},"gate":{"calls":1,"in":2,"out":971,"cache_r":14946,"cache_w":8091,"cost":0.07237779999999999,"dur_ms":15413}},"tok":981,"calls":2},{"t":"07-13 04:00","iso":"2026-07-13T04:00+09:00","by_src":{"breaking":{"calls":1,"in":2,"out":196,"cache_r":14946,"cache_w":8637,"cost":0.0646048,"dur_ms":5721},"gate":{"calls":1,"in":2,"out":410,"cache_r":14946,"cache_w":8003,"cost":0.0633658,"dur_ms":8843}},"tok":610,"calls":2},{"t":"07-13 04:20","iso":"2026-07-13T04:20+09:00","by_src":{"breaking":{"calls":1,"in":2,"out":6,"cache_r":14946,"cache_w":8530,"cost":0.0610388,"dur_ms":2838},"gate":{"calls":1,"in":2,"out":499,"cache_r":14946,"cache_w":8186,"cost":0.06595780000000001,"dur_ms":7589}},"tok":509,"calls":2},{"t":"07-13 04:30","iso":"2026-07-13T04:30+09:00","by_src":{"breaking":{"calls":1,"in":2,"out":6,"cache_r":14946,"cache_w":8668,"cost":0.0618398,"dur_ms":2413},"gate":{"calls":1,"in":2,"out":64,"cache_r":14946,"cache_w":8251,"cost":0.059772799999999994,"dur_ms":3186},"group":{"calls":1,"in":2,"out":13,"cache_r":11965,"cache_w":4647,"cost":0.0544395,"dur_ms":2361}},"tok":89,"calls":3},{"t":"07-13 04:50","iso":"2026-07-13T04:50+09:00","by_src":{"breaking":{"calls":1,"in":2,"out":11,"cache_r":14946,"cache_w":8514,"cost":0.06102780000000001,"dur_ms":2715},"gate":{"calls":1,"in":2,"out":2385,"cache_r":14946,"cache_w":8255,"cost":0.0947728,"dur_ms":33033},"group":{"calls":1,"in":2,"out":198,"cache_r":11965,"cache_w":4830,"cost":0.061007500000000006,"dur_ms":5343}},"tok":2600,"calls":3},{"t":"07-13 05:00","iso":"2026-07-13T05:00+09:00","by_src":{"breaking":{"calls":1,"in":2,"out":11,"cache_r":14946,"cache_w":8665,"cost":0.06189080000000001,"dur_ms":2198},"gate":{"calls":1,"in":2,"out":1285,"cache_r":14946,"cache_w":8448,"cost":0.0794768,"dur_ms":18247},"group":{"calls":1,"in":2,"out":7,"cache_r":11965,"cache_w":4372,"cost":0.0512445,"dur_ms":2240}},"tok":1309,"calls":3},{"t":"07-13 05:20","iso":"2026-07-13T05:20+09:00","by_src":{"breaking":{"calls":1,"in":2,"out":11,"cache_r":14946,"cache_w":8555,"cost":0.061316800000000005,"dur_ms":2008},"gate":{"calls":1,"in":2,"out":2091,"cache_r":14946,"cache_w":8560,"cost":0.09248579999999999,"dur_ms":30260},"group":{"calls":1,"in":2,"out":67,"cache_r":11965,"cache_w":4426,"cost":0.053318500000000005,"dur_ms":3100}},"tok":2175,"calls":3},{"t":"07-13 05:30","iso":"2026-07-13T05:30+09:00","by_src":{"breaking":{"calls":1,"in":2,"out":70,"cache_r":14946,"cache_w":8461,"cost":0.0615328,"dur_ms":2827},"gate":{"calls":1,"in":2,"out":1468,"cache_r":14946,"cache_w":8280,"cost":0.08111979999999999,"dur_ms":23173},"group":{"calls":1,"in":2,"out":119,"cache_r":11965,"cache_w":4743,"cost":0.057961500000000006,"dur_ms":6498}},"tok":1663,"calls":3},{"t":"07-13 05:50","iso":"2026-07-13T05:50+09:00","by_src":{"breaking":{"calls":1,"in":2,"out":307,"cache_r":14946,"cache_w":8950,"cost":0.0683188,"dur_ms":8638},"gate":{"calls":1,"in":2,"out":1161,"cache_r":14946,"cache_w":8366,"cost":0.0769828,"dur_ms":17177}},"tok":1472,"calls":2},{"t":"07-13 06:00","iso":"2026-07-13T06:00+09:00","by_src":{"breaking":{"calls":1,"in":2,"out":21,"cache_r":14946,"cache_w":8604,"cost":0.0618148,"dur_ms":2439},"gate":{"calls":1,"in":2,"out":2858,"cache_r":14946,"cache_w":8619,"cost":0.1044768,"dur_ms":40782},"group":{"calls":1,"in":2,"out":525,"cache_r":11965,"cache_w":4481,"cost":0.06540549999999999,"dur_ms":10040}},"tok":3410,"calls":3},{"t":"07-13 06:20","iso":"2026-07-13T06:20+09:00","by_src":{"breaking":{"calls":1,"in":2,"out":409,"cache_r":14946,"cache_w":8540,"cost":0.06714880000000001,"dur_ms":8176},"gate":{"calls":2,"in":4,"out":4910,"cache_r":29892,"cache_w":17539,"cost":0.1986066,"dur_ms":72637},"group":{"calls":1,"in":2,"out":303,"cache_r":11965,"cache_w":4945,"cost":0.06477649999999999,"dur_ms":7553}},"tok":5630,"calls":4},{"t":"07-13 06:30","iso":"2026-07-13T06:30+09:00","by_src":{"breaking":{"calls":1,"in":2,"out":369,"cache_r":14946,"cache_w":8792,"cost":0.0681488,"dur_ms":6664},"gate":{"calls":1,"in":2,"out":99,"cache_r":14946,"cache_w":8422,"cost":0.06150480000000001,"dur_ms":3212},"group":{"calls":1,"in":2,"out":13,"cache_r":11965,"cache_w":4631,"cost":0.05421449999999999,"dur_ms":2582}},"tok":487,"calls":3},{"t":"07-13 06:50","iso":"2026-07-13T06:50+09:00","by_src":{"breaking":{"calls":1,"in":2,"out":452,"cache_r":14946,"cache_w":8855,"cost":0.0698418,"dur_ms":8559},"gate":{"calls":1,"in":2,"out":1025,"cache_r":14946,"cache_w":8356,"cost":0.0749448,"dur_ms":16856},"group":{"calls":1,"in":2,"out":731,"cache_r":11965,"cache_w":4740,"cost":0.0734035,"dur_ms":14035}},"tok":2214,"calls":3},{"t":"07-13 07:00","iso":"2026-07-13T07:00+09:00","by_src":{"breaking":{"calls":1,"in":2,"out":11,"cache_r":14946,"cache_w":8507,"cost":0.060990800000000005,"dur_ms":2464},"gate":{"calls":1,"in":2,"out":2017,"cache_r":14946,"cache_w":8459,"cost":0.09070279999999999,"dur_ms":28103},"group":{"calls":1,"in":2,"out":428,"cache_r":11965,"cache_w":4817,"cost":0.0666125,"dur_ms":9540},"autopick":{"calls":1,"in":2,"out":329,"cache_r":11965,"cache_w":86804,"cost":0.8822575,"dur_ms":8334}},"tok":2793,"calls":4},{"t":"07-13 07:10","iso":"2026-07-13T07:10+09:00","by_src":{"analyze":{"calls":1,"in":8,"out":17266,"cache_r":480102,"cache_w":143798,"cost":2.1343449999999997,"dur_ms":275156}},"tok":17274,"calls":1},{"t":"07-13 07:20","iso":"2026-07-13T07:20+09:00","by_src":{"breaking":{"calls":1,"in":2,"out":11,"cache_r":14946,"cache_w":8490,"cost":0.0555948,"dur_ms":2512},"gate":{"calls":1,"in":2,"out":2753,"cache_r":14946,"cache_w":8321,"cost":0.1007818,"dur_ms":42876},"group":{"calls":1,"in":2,"out":348,"cache_r":11965,"cache_w":4698,"cost":0.0633405,"dur_ms":8045}},"tok":3118,"calls":3},{"t":"07-13 07:30","iso":"2026-07-13T07:30+09:00","by_src":{"breaking":{"calls":1,"in":2,"out":16,"cache_r":14946,"cache_w":8544,"cost":0.0613178,"dur_ms":1830},"gate":{"calls":1,"in":2,"out":1292,"cache_r":14946,"cache_w":8094,"cost":0.0772798,"dur_ms":20976}},"tok":1312,"calls":2},{"t":"07-13 07:50","iso":"2026-07-13T07:50+09:00","by_src":{"breaking":{"calls":1,"in":2,"out":11,"cache_r":14946,"cache_w":8544,"cost":0.0559188,"dur_ms":1768},"gate":{"calls":1,"in":2,"out":3491,"cache_r":14946,"cache_w":8466,"cost":0.11282279999999999,"dur_ms":46066},"group":{"calls":1,"in":2,"out":292,"cache_r":11965,"cache_w":4736,"cost":0.0623605,"dur_ms":7442},"autopick":{"calls":1,"in":2,"out":5,"cache_r":11965,"cache_w":86841,"cost":0.8745275,"dur_ms":6509}},"tok":3807,"calls":4}]}